README
setup.py
librato/__init__.py
librato/aggregator.py
librato/alerts.py
librato/annotations.py
librato/exceptions.py
librato/metrics.py
librato/queue.py
librato/spaces.py
librato/streams.py
librato_metrics.egg-info/PKG-INFO
librato_metrics.egg-info/SOURCES.txt
librato_metrics.egg-info/dependency_links.txt
librato_metrics.egg-info/requires.txt
librato_metrics.egg-info/top_level.txt