Metadata-Version: 1.1
Name: librato-metrics
Version: 3.1.0
Summary: Python API Wrapper for Librato
Home-page: http://github.com/librato/python-librato
Author: Librato
Author-email: support@librato.com
License: https://github.com/librato/python-librato/blob/master/LICENSE
Platform: Posix; MacOS X; Windows
Classifier: Development Status :: 3 - Alpha
Classifier: Intended Audience :: Developers
Classifier: License :: OSI Approved :: MIT License
Classifier: Operating System :: OS Independent
Classifier: Topic :: Internet
Classifier: Programming Language :: Python
Classifier: Programming Language :: Python :: 3
